MANIFEST.in
README.md
btHook.py
btNode.py
btPostRequest.py
btStreamingNode.py
setup.cfg
setup.py
btnexus_node_python.egg-info/PKG-INFO
btnexus_node_python.egg-info/SOURCES.txt
btnexus_node_python.egg-info/dependency_links.txt
btnexus_node_python.egg-info/requires.txt
btnexus_node_python.egg-info/top_level.txt
examples/__init__.py
examples/audioFileStreamingNode.py
examples/audioStreamingNode.py
examples/googleHelper.py
examples/listeningNode.py
examples/listeningNodeIO.py
examples/sendingNode.py
examples/sendingNodeIO.py
nexus/__init__.py
nexus/btCaptions.py
nexus/btNexusData.py
nexus/btNexusMemory.py
nexus/hookSettings.py
nexus/message.py
nexus/nexusConnector.py
nexus/nexusExceptions.py
nexus/postRequest.py
nexus/protocols/__init__.py
nexus/protocols/audioStreamFactory.py
nexus/protocols/audioStreamProtocol.py
tests/__init__.py
tests/reconnectUtils.py
tests/testBTPostRequest.py
tests/testChatIntegration.py
tests/testHook.py
tests/testNode.py