Metadata-Version: 2.1
Name: btnexus-node-python
Version: 6.2.228
Summary: Provides Node, Hook and PostRequests that follow the btProtocol.
Home-page: https://github.com/Blackout-Technologies/btnexus-node-python
Author: Blackout Technologies
Author-email: dev@blackout.ai
License: UNKNOWN
Platform: UNKNOWN
Classifier: License :: OSI Approved :: GNU Lesser General Public License v3 or later (LGPLv3+)
Classifier: Programming Language :: Python :: 3.6
Classifier: Programming Language :: Python :: 3.7
